maleo/dtos/__init__.py
maleo/dtos/authentication.py
maleo/dtos/authorization.py
maleo/dtos/credential.py
maleo/dtos/data.py
maleo/dtos/descriptor.py
maleo/dtos/impersonation.py
maleo/dtos/metadata.py
maleo/dtos/pagination.py
maleo/dtos/parameter.py
maleo/dtos/payload.py
maleo/dtos/resource.py
maleo/dtos/service.py
maleo/dtos/settings.py
maleo/dtos/token.py
maleo/dtos/error/__init__.py
maleo/dtos/error/metadata.py
maleo/dtos/error/spec.py
maleo/dtos/key/__init__.py
maleo/dtos/key/rsa.py
maleo_dtos-0.0.25.dist-info/licenses/LICENSE
maleo_dtos-0.0.25.dist-info/METADATA
maleo_dtos-0.0.25.dist-info/WHEEL
maleo_dtos-0.0.25.dist-info/top_level.txt
maleo_dtos-0.0.25.dist-info/RECORD
